astroabc/__init__.py
astroabc/abc_class.py
astroabc/io_utils.py
astroabc/model.py
astroabc/mpi_pool.py
astroabc/mpi_test.py
astroabc/myutils.py
astroabc/priors.py
astroabc/setup_mpi_mp.py
astroabc/tests.py
astroabc/tolerance.py
astroabc/variance.py
examples/bin_data.py
examples/distance_calc.py
examples/gaussian.py
examples/gaussian_splitcomm.py
examples/parse_params.py
astroabc-1.5.0.dist-info/LICENSE.txt
astroabc-1.5.0.dist-info/METADATA
astroabc-1.5.0.dist-info/WHEEL
astroabc-1.5.0.dist-info/top_level.txt
astroabc-1.5.0.dist-info/RECORD
