Metadata-Version: 1.1
Name: astroabc
Version: 1.5.0
Summary: A Python implementation of an Approximate Bayesian Computation Sequential Monte Carlo (ABC SMC) sampler for parameter estimation.
Home-page: https://github.com/EliseJ/astroABC
Author: Elise Jennings
Author-email: elise.jennings@gmail.com 
License: MIT
Platform: UNKNOWN
Classifier: Development Status :: 5 - Production/Stable
Classifier: Environment :: Console
Classifier: Operating System :: OS Independent
Classifier: Intended Audience :: Science/Research
Classifier: License :: OSI Approved :: MIT License
Classifier: Programming Language :: Python :: 3.6
Classifier: Topic :: Scientific/Engineering
Requires: NumPy (>=2.7)
